typpy/__init__.py
typpy/__main__.py
typpy/discover_files.py
typpy/error.py
typpy/format.py
typpy/is_subtype.py
typpy/output.py
typpy/py.typed
typpy/resolver.py
typpy/scope.py
typpy/type_checker.py
typpy-0.4.0.dist-info/LICENSE
typpy-0.4.0.dist-info/METADATA
typpy-0.4.0.dist-info/WHEEL
typpy-0.4.0.dist-info/entry_points.txt
typpy-0.4.0.dist-info/top_level.txt
typpy-0.4.0.dist-info/RECORD
