Metadata-Version: 2.1
Name: typpy
Version: 0.4.0
Summary: Python Type Checker
Home-page: https://github.com/frapa/typpy
Author: Francesco Pasa
Author-email: francescopasa@gmail.com
License: GPL3
Platform: UNKNOWN
Classifier: License :: OSI Approved :: GNU General Public License v3 (GPLv3)
Classifier: Programming Language :: Python :: 3
Classifier: Programming Language :: Python :: 3.6
Classifier: Programming Language :: Python :: 3.7
Classifier: Programming Language :: Python :: 3.8
Classifier: Programming Language :: Python :: 3.9
Classifier: Typing :: Typed
Requires-Dist: colorama (~=0.4)
